{
  "source": "Sina Market Center",
  "source_url": "https://vip.stock.finance.sina.com.cn/quotes_service/api/json_v2.php/Market_Center.getHQFuturesData?page=1&num=100&sort=position&asc=0&node=zly_qh&base=futures",
  "symbol": "P0",
  "market": "DCE",
  "updated_at_utc": "2026-07-14T13:29:16+00:00",
  "trading_day": "2026-07-15",
  "market_time": "21:29:08",
  "continuous": {
    "symbol": "P0",
    "name": "棕榈油连续",
    "price": 9326.0,
    "open": 9370.0,
    "high": 9371.0,
    "low": 9322.0,
    "volume": 69001,
    "open_interest": 473486,
    "prev_close": 9351.0,
    "prev_settlement": 9277.0,
    "reference_price": 9277.0,
    "reference_type": "previous_settlement",
    "change": 49.0,
    "change_ratio": 0.00528188,
    "change_pct": "+0.53%",
    "bid_price": 9327.0,
    "ask_price": 9328.0,
    "bid_volume": 2,
    "ask_volume": 74,
    "tradedate": "2026-07-15",
    "ticktime": "21:29:08"
  },
  "main": {
    "symbol": "P2609",
    "name": "棕榈油2609",
    "price": 9326.0,
    "open": 9370.0,
    "high": 9371.0,
    "low": 9322.0,
    "volume": 69001,
    "open_interest": 473486,
    "prev_close": 9351.0,
    "prev_settlement": 9277.0,
    "reference_price": 9277.0,
    "reference_type": "previous_settlement",
    "change": 49.0,
    "change_ratio": 0.00528188,
    "change_pct": "+0.53%",
    "bid_price": 9327.0,
    "ask_price": 9328.0,
    "bid_volume": 2,
    "ask_volume": 74,
    "tradedate": "2026-07-15",
    "ticktime": "21:29:08"
  },
  "secondary": {
    "symbol": "P2701",
    "name": "棕榈油2701",
    "price": 9615.0,
    "open": 9639.0,
    "high": 9648.0,
    "low": 9610.0,
    "volume": 13643,
    "open_interest": 221182,
    "prev_close": 9638.0,
    "prev_settlement": 9579.0,
    "reference_price": 9579.0,
    "reference_type": "previous_settlement",
    "change": 36.0,
    "change_ratio": 0.00375822,
    "change_pct": "+0.38%",
    "bid_price": 9614.0,
    "ask_price": 9615.0,
    "bid_volume": 21,
    "ask_volume": 2,
    "tradedate": "2026-07-15",
    "ticktime": "21:29:08"
  },
  "mapping_verified": true,
  "mapping_note": "P0 当前行情与 P2609 的价格及持仓一致。",
  "main_open_interest_share": 0.5589,
  "secondary_open_interest_ratio": 0.4671,
  "secondary_spread": 289.0,
  "secondary_spread_ratio": 0.030989,
  "spread_structure": "远月升水",
  "months_to_delivery_month": 2,
  "roll_state": "watch",
  "roll_label": "监控移仓",
  "roll_score": 50,
  "roll_reason": "主力进入交割月前约两个月或次主力持仓超过主力一半。",
  "contract_specs": {
    "multiplier": 10,
    "tick_size": 1,
    "price_unit": "元/吨",
    "tick_value": 10,
    "rule_reference": "大商所〔2026〕32号",
    "effective_from": "2026-04-10",
    "source_url": "https://www.dce.com.cn/dce/content/2026/ywggytz/18628268.html"
  },
  "candidates": [
    {
      "symbol": "P2609",
      "name": "棕榈油2609",
      "price": 9326.0,
      "open": 9370.0,
      "high": 9371.0,
      "low": 9322.0,
      "volume": 69001,
      "open_interest": 473486,
      "prev_close": 9351.0,
      "prev_settlement": 9277.0,
      "reference_price": 9277.0,
      "reference_type": "previous_settlement",
      "change": 49.0,
      "change_ratio": 0.00528188,
      "change_pct": "+0.53%",
      "bid_price": 9327.0,
      "ask_price": 9328.0,
      "bid_volume": 2,
      "ask_volume": 74,
      "tradedate": "2026-07-15",
      "ticktime": "21:29:08"
    },
    {
      "symbol": "P2701",
      "name": "棕榈油2701",
      "price": 9615.0,
      "open": 9639.0,
      "high": 9648.0,
      "low": 9610.0,
      "volume": 13643,
      "open_interest": 221182,
      "prev_close": 9638.0,
      "prev_settlement": 9579.0,
      "reference_price": 9579.0,
      "reference_type": "previous_settlement",
      "change": 36.0,
      "change_ratio": 0.00375822,
      "change_pct": "+0.38%",
      "bid_price": 9614.0,
      "ask_price": 9615.0,
      "bid_volume": 21,
      "ask_volume": 2,
      "tradedate": "2026-07-15",
      "ticktime": "21:29:08"
    },
    {
      "symbol": "P2610",
      "name": "棕榈油连续",
      "price": 9391.0,
      "open": 9412.0,
      "high": 9421.0,
      "low": 9388.0,
      "volume": 286,
      "open_interest": 35515,
      "prev_close": 9414.0,
      "prev_settlement": 9343.0,
      "reference_price": 9343.0,
      "reference_type": "previous_settlement",
      "change": 48.0,
      "change_ratio": 0.00513754,
      "change_pct": "+0.51%",
      "bid_price": 9386.0,
      "ask_price": 9390.0,
      "bid_volume": 24,
      "ask_volume": 10,
      "tradedate": "2026-07-15",
      "ticktime": "21:29:08"
    },
    {
      "symbol": "P2611",
      "name": "棕榈油2611",
      "price": 9443.0,
      "open": 9470.0,
      "high": 9470.0,
      "low": 9443.0,
      "volume": 455,
      "open_interest": 33855,
      "prev_close": 9464.0,
      "prev_settlement": 9408.0,
      "reference_price": 9408.0,
      "reference_type": "previous_settlement",
      "change": 35.0,
      "change_ratio": 0.00372024,
      "change_pct": "+0.37%",
      "bid_price": 9441.0,
      "ask_price": 9445.0,
      "bid_volume": 17,
      "ask_volume": 5,
      "tradedate": "2026-07-15",
      "ticktime": "21:29:08"
    },
    {
      "symbol": "P2705",
      "name": "棕榈油2705",
      "price": 9641.0,
      "open": 9660.0,
      "high": 9670.0,
      "low": 9638.0,
      "volume": 1549,
      "open_interest": 31658,
      "prev_close": 9654.0,
      "prev_settlement": 9613.0,
      "reference_price": 9613.0,
      "reference_type": "previous_settlement",
      "change": 28.0,
      "change_ratio": 0.00291272,
      "change_pct": "+0.29%",
      "bid_price": 9639.0,
      "ask_price": 9643.0,
      "bid_volume": 2,
      "ask_volume": 3,
      "tradedate": "2026-07-15",
      "ticktime": "21:29:07"
    },
    {
      "symbol": "P2608",
      "name": "棕榈油2608",
      "price": 9171.0,
      "open": 9196.0,
      "high": 9210.0,
      "low": 9170.0,
      "volume": 1007,
      "open_interest": 25290,
      "prev_close": 9198.0,
      "prev_settlement": 9127.0,
      "reference_price": 9127.0,
      "reference_type": "previous_settlement",
      "change": 44.0,
      "change_ratio": 0.00482086,
      "change_pct": "+0.48%",
      "bid_price": 9171.0,
      "ask_price": 9173.0,
      "bid_volume": 6,
      "ask_volume": 7,
      "tradedate": "2026-07-15",
      "ticktime": "21:29:08"
    }
  ]
}