{
  "source": "Sina Market Center",
  "source_url": "https://vip.stock.finance.sina.com.cn/quotes_service/api/json_v2.php/Market_Center.getHQFuturesData?page=1&num=100&sort=position&asc=0&node=zly_qh&base=futures",
  "symbol": "P0",
  "market": "DCE",
  "updated_at_utc": "2026-07-19T01:10:16+00:00",
  "trading_day": "2026-07-20",
  "market_time": "23:00:00",
  "continuous": {
    "symbol": "P0",
    "name": "棕榈油连续",
    "price": 9312.0,
    "open": 9260.0,
    "high": 9315.0,
    "low": 9253.0,
    "volume": 174728,
    "open_interest": 460238,
    "prev_close": 9232.0,
    "prev_settlement": 9245.0,
    "reference_price": 9245.0,
    "reference_type": "previous_settlement",
    "change": 67.0,
    "change_ratio": 0.00724716,
    "change_pct": "+0.72%",
    "bid_price": 9309.0,
    "ask_price": 9312.0,
    "bid_volume": 14,
    "ask_volume": 2,
    "tradedate": "2026-07-20",
    "ticktime": "23:00:00"
  },
  "main": {
    "symbol": "P2609",
    "name": "棕榈油2609",
    "price": 9312.0,
    "open": 9260.0,
    "high": 9315.0,
    "low": 9253.0,
    "volume": 174728,
    "open_interest": 460238,
    "prev_close": 9232.0,
    "prev_settlement": 9245.0,
    "reference_price": 9245.0,
    "reference_type": "previous_settlement",
    "change": 67.0,
    "change_ratio": 0.00724716,
    "change_pct": "+0.72%",
    "bid_price": 9309.0,
    "ask_price": 9312.0,
    "bid_volume": 14,
    "ask_volume": 2,
    "tradedate": "2026-07-20",
    "ticktime": "23:00:00"
  },
  "secondary": {
    "symbol": "P2701",
    "name": "棕榈油2701",
    "price": 9614.0,
    "open": 9552.0,
    "high": 9615.0,
    "low": 9549.0,
    "volume": 48396,
    "open_interest": 222511,
    "prev_close": 9530.0,
    "prev_settlement": 9535.0,
    "reference_price": 9535.0,
    "reference_type": "previous_settlement",
    "change": 79.0,
    "change_ratio": 0.00828526,
    "change_pct": "+0.83%",
    "bid_price": 9610.0,
    "ask_price": 9613.0,
    "bid_volume": 313,
    "ask_volume": 1,
    "tradedate": "2026-07-20",
    "ticktime": "23:00:00"
  },
  "mapping_verified": true,
  "mapping_note": "P0 当前行情与 P2609 的价格及持仓一致。",
  "main_open_interest_share": 0.5569,
  "secondary_open_interest_ratio": 0.4835,
  "secondary_spread": 302.0,
  "secondary_spread_ratio": 0.032431,
  "spread_structure": "远月升水",
  "months_to_delivery_month": 2,
  "roll_state": "watch",
  "roll_label": "监控移仓",
  "roll_score": 50,
  "roll_reason": "主力进入交割月前约两个月或次主力持仓超过主力一半。",
  "contract_specs": {
    "multiplier": 10,
    "tick_size": 1,
    "price_unit": "元/吨",
    "tick_value": 10,
    "rule_reference": "大商所〔2026〕32号",
    "effective_from": "2026-04-10",
    "source_url": "https://www.dce.com.cn/dce/content/2026/ywggytz/18628268.html"
  },
  "candidates": [
    {
      "symbol": "P2609",
      "name": "棕榈油2609",
      "price": 9312.0,
      "open": 9260.0,
      "high": 9315.0,
      "low": 9253.0,
      "volume": 174728,
      "open_interest": 460238,
      "prev_close": 9232.0,
      "prev_settlement": 9245.0,
      "reference_price": 9245.0,
      "reference_type": "previous_settlement",
      "change": 67.0,
      "change_ratio": 0.00724716,
      "change_pct": "+0.72%",
      "bid_price": 9309.0,
      "ask_price": 9312.0,
      "bid_volume": 14,
      "ask_volume": 2,
      "tradedate": "2026-07-20",
      "ticktime": "23:00:00"
    },
    {
      "symbol": "P2701",
      "name": "棕榈油2701",
      "price": 9614.0,
      "open": 9552.0,
      "high": 9615.0,
      "low": 9549.0,
      "volume": 48396,
      "open_interest": 222511,
      "prev_close": 9530.0,
      "prev_settlement": 9535.0,
      "reference_price": 9535.0,
      "reference_type": "previous_settlement",
      "change": 79.0,
      "change_ratio": 0.00828526,
      "change_pct": "+0.83%",
      "bid_price": 9610.0,
      "ask_price": 9613.0,
      "bid_volume": 313,
      "ask_volume": 1,
      "tradedate": "2026-07-20",
      "ticktime": "23:00:00"
    },
    {
      "symbol": "P2705",
      "name": "棕榈油2705",
      "price": 9647.0,
      "open": 9590.0,
      "high": 9652.0,
      "low": 9590.0,
      "volume": 8874,
      "open_interest": 39971,
      "prev_close": 9568.0,
      "prev_settlement": 9584.0,
      "reference_price": 9584.0,
      "reference_type": "previous_settlement",
      "change": 63.0,
      "change_ratio": 0.00657346,
      "change_pct": "+0.66%",
      "bid_price": 9645.0,
      "ask_price": 9652.0,
      "bid_volume": 5,
      "ask_volume": 10,
      "tradedate": "2026-07-20",
      "ticktime": "23:00:00"
    },
    {
      "symbol": "P2610",
      "name": "棕榈油连续",
      "price": 9372.0,
      "open": 9311.0,
      "high": 9373.0,
      "low": 9311.0,
      "volume": 933,
      "open_interest": 36100,
      "prev_close": 9295.0,
      "prev_settlement": 9305.0,
      "reference_price": 9305.0,
      "reference_type": "previous_settlement",
      "change": 67.0,
      "change_ratio": 0.00720043,
      "change_pct": "+0.72%",
      "bid_price": 9364.0,
      "ask_price": 9474.0,
      "bid_volume": 2,
      "ask_volume": 1,
      "tradedate": "2026-07-20",
      "ticktime": "22:59:58"
    },
    {
      "symbol": "P2611",
      "name": "棕榈油2611",
      "price": 9430.0,
      "open": 9388.0,
      "high": 9430.0,
      "low": 9371.0,
      "volume": 891,
      "open_interest": 35041,
      "prev_close": 9347.0,
      "prev_settlement": 9364.0,
      "reference_price": 9364.0,
      "reference_type": "previous_settlement",
      "change": 66.0,
      "change_ratio": 0.00704827,
      "change_pct": "+0.70%",
      "bid_price": 9398.0,
      "ask_price": 9450.0,
      "bid_volume": 1,
      "ask_volume": 1,
      "tradedate": "2026-07-20",
      "ticktime": "22:59:59"
    },
    {
      "symbol": "P2612",
      "name": "棕榈油2612",
      "price": 9518.0,
      "open": 9469.0,
      "high": 9519.0,
      "low": 9457.0,
      "volume": 519,
      "open_interest": 21087,
      "prev_close": 9434.0,
      "prev_settlement": 9438.0,
      "reference_price": 9438.0,
      "reference_type": "previous_settlement",
      "change": 80.0,
      "change_ratio": 0.00847637,
      "change_pct": "+0.85%",
      "bid_price": 9393.0,
      "ask_price": 9550.0,
      "bid_volume": 1,
      "ask_volume": 1,
      "tradedate": "2026-07-20",
      "ticktime": "22:59:58"
    }
  ]
}