{
  "source": "AKShare futures_zh_minute_sina",
  "symbol": "P0",
  "updated_at_utc": "2026-06-29T09:52:21+00:00",
  "one_hour": {
    "label": "1小时",
    "latest_time": "2026-06-29 15:00:00",
    "open": 9370.0,
    "high": 9405.0,
    "low": 9369.0,
    "close": 9379.0,
    "change_pct": "+0.10%",
    "volume": 233,
    "rsi14": 59.05,
    "bollinger": {
      "period": 20,
      "close": 9379.0,
      "upper": 9439.49,
      "mid": 9261.25,
      "lower": 9083.01,
      "band_width": 0.0385,
      "position": "中轨上方"
    },
    "high20": 9405.0,
    "low20": 9029.0,
    "last_30_bars": [
      {
        "datetime": "2026-06-22 22:00:00",
        "open": 9353.0,
        "high": 9402.0,
        "low": 9353.0,
        "close": 9395.0,
        "volume": 124795,
        "hold": 514303
      },
      {
        "datetime": "2026-06-22 23:00:00",
        "open": 9395.0,
        "high": 9417.0,
        "low": 9377.0,
        "close": 9383.0,
        "volume": 51151,
        "hold": 506726
      },
      {
        "datetime": "2026-06-23 10:00:00",
        "open": 9387.0,
        "high": 9469.0,
        "low": 9380.0,
        "close": 9433.0,
        "volume": 153183,
        "hold": 506627
      },
      {
        "datetime": "2026-06-23 11:15:00",
        "open": 9433.0,
        "high": 9455.0,
        "low": 9339.0,
        "close": 9367.0,
        "volume": 104953,
        "hold": 498282
      },
      {
        "datetime": "2026-06-23 14:15:00",
        "open": 9371.0,
        "high": 9390.0,
        "low": 9292.0,
        "close": 9306.0,
        "volume": 144873,
        "hold": 494655
      },
      {
        "datetime": "2026-06-23 15:00:00",
        "open": 9305.0,
        "high": 9315.0,
        "low": 9274.0,
        "close": 9308.0,
        "volume": 88,
        "hold": 495108
      },
      {
        "datetime": "2026-06-23 22:00:00",
        "open": 9302.0,
        "high": 9323.0,
        "low": 9262.0,
        "close": 9308.0,
        "volume": 137098,
        "hold": 510096
      },
      {
        "datetime": "2026-06-23 23:00:00",
        "open": 9308.0,
        "high": 9335.0,
        "low": 9299.0,
        "close": 9318.0,
        "volume": 43672,
        "hold": 503770
      },
      {
        "datetime": "2026-06-24 10:00:00",
        "open": 9322.0,
        "high": 9395.0,
        "low": 9308.0,
        "close": 9369.0,
        "volume": 120208,
        "hold": 500724
      },
      {
        "datetime": "2026-06-24 11:15:00",
        "open": 9368.0,
        "high": 9390.0,
        "low": 9332.0,
        "close": 9343.0,
        "volume": 47284,
        "hold": 497512
      },
      {
        "datetime": "2026-06-24 14:15:00",
        "open": 9342.0,
        "high": 9355.0,
        "low": 9307.0,
        "close": 9341.0,
        "volume": 80599,
        "hold": 497958
      },
      {
        "datetime": "2026-06-24 15:00:00",
        "open": 9340.0,
        "high": 9342.0,
        "low": 9307.0,
        "close": 9335.0,
        "volume": 48739,
        "hold": 496832
      },
      {
        "datetime": "2026-06-24 22:00:00",
        "open": 9287.0,
        "high": 9299.0,
        "low": 9172.0,
        "close": 9188.0,
        "volume": 236155,
        "hold": 529414
      },
      {
        "datetime": "2026-06-24 23:00:00",
        "open": 9184.0,
        "high": 9254.0,
        "low": 9184.0,
        "close": 9202.0,
        "volume": 75544,
        "hold": 526022
      },
      {
        "datetime": "2026-06-25 10:00:00",
        "open": 9185.0,
        "high": 9202.0,
        "low": 9029.0,
        "close": 9057.0,
        "volume": 19294,
        "hold": 553179
      },
      {
        "datetime": "2026-06-25 11:15:00",
        "open": 9057.0,
        "high": 9137.0,
        "low": 9039.0,
        "close": 9136.0,
        "volume": 145428,
        "hold": 546053
      },
      {
        "datetime": "2026-06-25 14:15:00",
        "open": 9137.0,
        "high": 9142.0,
        "low": 9095.0,
        "close": 9118.0,
        "volume": 58548,
        "hold": 546056
      },
      {
        "datetime": "2026-06-25 15:00:00",
        "open": 9118.0,
        "high": 9160.0,
        "low": 9098.0,
        "close": 9160.0,
        "volume": 40589,
        "hold": 540897
      },
      {
        "datetime": "2026-06-25 22:00:00",
        "open": 9160.0,
        "high": 9240.0,
        "low": 9144.0,
        "close": 9240.0,
        "volume": 184801,
        "hold": 540587
      },
      {
        "datetime": "2026-06-25 23:00:00",
        "open": 9240.0,
        "high": 9286.0,
        "low": 9225.0,
        "close": 9286.0,
        "volume": 79464,
        "hold": 531473
      },
      {
        "datetime": "2026-06-26 10:00:00",
        "open": 9294.0,
        "high": 9329.0,
        "low": 9256.0,
        "close": 9281.0,
        "volume": 138600,
        "hold": 516768
      },
      {
        "datetime": "2026-06-26 11:15:00",
        "open": 9282.0,
        "high": 9294.0,
        "low": 9241.0,
        "close": 9251.0,
        "volume": 31934,
        "hold": 511867
      },
      {
        "datetime": "2026-06-26 14:15:00",
        "open": 9251.0,
        "high": 9325.0,
        "low": 9235.0,
        "close": 9313.0,
        "volume": 123411,
        "hold": 512674
      },
      {
        "datetime": "2026-06-26 15:00:00",
        "open": 9313.0,
        "high": 9338.0,
        "low": 9292.0,
        "close": 9315.0,
        "volume": 133,
        "hold": 502227
      },
      {
        "datetime": "2026-06-26 22:00:00",
        "open": 9273.0,
        "high": 9302.0,
        "low": 9262.0,
        "close": 9277.0,
        "volume": 113887,
        "hold": 506998
      },
      {
        "datetime": "2026-06-26 23:00:00",
        "open": 9277.0,
        "high": 9285.0,
        "low": 9244.0,
        "close": 9270.0,
        "volume": 102,
        "hold": 500503
      },
      {
        "datetime": "2026-06-29 10:00:00",
        "open": 9282.0,
        "high": 9379.0,
        "low": 9272.0,
        "close": 9351.0,
        "volume": 209420,
        "hold": 498444
      },
      {
        "datetime": "2026-06-29 11:15:00",
        "open": 9353.0,
        "high": 9371.0,
        "low": 9332.0,
        "close": 9355.0,
        "volume": 7,
        "hold": 495614
      },
      {
        "datetime": "2026-06-29 14:15:00",
        "open": 9355.0,
        "high": 9374.0,
        "low": 9336.0,
        "close": 9370.0,
        "volume": 28,
        "hold": 494213
      },
      {
        "datetime": "2026-06-29 15:00:00",
        "open": 9370.0,
        "high": 9405.0,
        "low": 9369.0,
        "close": 9379.0,
        "volume": 233,
        "hold": 487520
      }
    ]
  },
  "two_hour": {
    "label": "2小时",
    "latest_time": "2026-06-29 15:00:00",
    "open": 9355.0,
    "high": 9405.0,
    "low": 9336.0,
    "close": 9379.0,
    "change_pct": "+0.26%",
    "volume": 233,
    "rsi14": 55.05,
    "bollinger": {
      "period": 20,
      "close": 9379.0,
      "upper": 9449.77,
      "mid": 9305.8,
      "lower": 9161.83,
      "band_width": 0.0309,
      "position": "中轨上方"
    },
    "high20": 9469.0,
    "low20": 9029.0,
    "last_30_bars": [
      {
        "datetime": "2026-06-12 15:00:00",
        "open": 9392.0,
        "high": 9404.0,
        "low": 9307.0,
        "close": 9321.0,
        "volume": 103274,
        "hold": 538988
      },
      {
        "datetime": "2026-06-12 23:00:00",
        "open": 9283.0,
        "high": 9324.0,
        "low": 9280.0,
        "close": 9308.0,
        "volume": 24261,
        "hold": 541642
      },
      {
        "datetime": "2026-06-15 11:15:00",
        "open": 9260.0,
        "high": 9307.0,
        "low": 9166.0,
        "close": 9220.0,
        "volume": 121036,
        "hold": 552494
      },
      {
        "datetime": "2026-06-15 15:00:00",
        "open": 9220.0,
        "high": 9250.0,
        "low": 9215.0,
        "close": 9232.0,
        "volume": 35950,
        "hold": 546990
      },
      {
        "datetime": "2026-06-15 23:00:00",
        "open": 9197.0,
        "high": 9219.0,
        "low": 9151.0,
        "close": 9216.0,
        "volume": 37035,
        "hold": 551253
      },
      {
        "datetime": "2026-06-16 11:15:00",
        "open": 9238.0,
        "high": 9290.0,
        "low": 9216.0,
        "close": 9282.0,
        "volume": 92010,
        "hold": 552463
      },
      {
        "datetime": "2026-06-16 15:00:00",
        "open": 9283.0,
        "high": 9384.0,
        "low": 9244.0,
        "close": 9357.0,
        "volume": 189628,
        "hold": 541107
      },
      {
        "datetime": "2026-06-16 23:00:00",
        "open": 9334.0,
        "high": 9429.0,
        "low": 9330.0,
        "close": 9348.0,
        "volume": 71791,
        "hold": 529575
      },
      {
        "datetime": "2026-06-17 11:15:00",
        "open": 9343.0,
        "high": 9373.0,
        "low": 9312.0,
        "close": 9343.0,
        "volume": 99411,
        "hold": 529279
      },
      {
        "datetime": "2026-06-17 15:00:00",
        "open": 9341.0,
        "high": 9380.0,
        "low": 9328.0,
        "close": 9349.0,
        "volume": 110938,
        "hold": 526043
      },
      {
        "datetime": "2026-06-17 23:00:00",
        "open": 9370.0,
        "high": 9411.0,
        "low": 9358.0,
        "close": 9391.0,
        "volume": 843,
        "hold": 523606
      },
      {
        "datetime": "2026-06-18 11:15:00",
        "open": 9369.0,
        "high": 9369.0,
        "low": 9267.0,
        "close": 9268.0,
        "volume": 14679,
        "hold": 521007
      },
      {
        "datetime": "2026-06-18 15:00:00",
        "open": 9268.0,
        "high": 9316.0,
        "low": 9221.0,
        "close": 9301.0,
        "volume": 163,
        "hold": 513300
      },
      {
        "datetime": "2026-06-22 11:15:00",
        "open": 9374.0,
        "high": 9419.0,
        "low": 9342.0,
        "close": 9382.0,
        "volume": 36978,
        "hold": 513611
      },
      {
        "datetime": "2026-06-22 15:00:00",
        "open": 9381.0,
        "high": 9388.0,
        "low": 9318.0,
        "close": 9366.0,
        "volume": 701,
        "hold": 506497
      },
      {
        "datetime": "2026-06-22 23:00:00",
        "open": 9353.0,
        "high": 9417.0,
        "low": 9353.0,
        "close": 9383.0,
        "volume": 51151,
        "hold": 506726
      },
      {
        "datetime": "2026-06-23 11:15:00",
        "open": 9387.0,
        "high": 9469.0,
        "low": 9339.0,
        "close": 9367.0,
        "volume": 104953,
        "hold": 498282
      },
      {
        "datetime": "2026-06-23 15:00:00",
        "open": 9371.0,
        "high": 9390.0,
        "low": 9274.0,
        "close": 9308.0,
        "volume": 88,
        "hold": 495108
      },
      {
        "datetime": "2026-06-23 23:00:00",
        "open": 9302.0,
        "high": 9335.0,
        "low": 9262.0,
        "close": 9318.0,
        "volume": 43672,
        "hold": 503770
      },
      {
        "datetime": "2026-06-24 11:15:00",
        "open": 9322.0,
        "high": 9395.0,
        "low": 9308.0,
        "close": 9343.0,
        "volume": 47284,
        "hold": 497512
      },
      {
        "datetime": "2026-06-24 15:00:00",
        "open": 9342.0,
        "high": 9355.0,
        "low": 9307.0,
        "close": 9335.0,
        "volume": 129431,
        "hold": 496832
      },
      {
        "datetime": "2026-06-24 23:00:00",
        "open": 9287.0,
        "high": 9299.0,
        "low": 9172.0,
        "close": 9202.0,
        "volume": 75544,
        "hold": 526022
      },
      {
        "datetime": "2026-06-25 11:15:00",
        "open": 9185.0,
        "high": 9202.0,
        "low": 9029.0,
        "close": 9136.0,
        "volume": 164729,
        "hold": 546053
      },
      {
        "datetime": "2026-06-25 15:00:00",
        "open": 9137.0,
        "high": 9160.0,
        "low": 9095.0,
        "close": 9160.0,
        "volume": 99147,
        "hold": 540897
      },
      {
        "datetime": "2026-06-25 23:00:00",
        "open": 9160.0,
        "high": 9286.0,
        "low": 9144.0,
        "close": 9286.0,
        "volume": 79464,
        "hold": 531473
      },
      {
        "datetime": "2026-06-26 11:15:00",
        "open": 9294.0,
        "high": 9329.0,
        "low": 9241.0,
        "close": 9251.0,
        "volume": 31934,
        "hold": 511867
      },
      {
        "datetime": "2026-06-26 15:00:00",
        "open": 9251.0,
        "high": 9338.0,
        "low": 9235.0,
        "close": 9315.0,
        "volume": 133,
        "hold": 502227
      },
      {
        "datetime": "2026-06-26 23:00:00",
        "open": 9273.0,
        "high": 9302.0,
        "low": 9244.0,
        "close": 9270.0,
        "volume": 102,
        "hold": 500503
      },
      {
        "datetime": "2026-06-29 11:15:00",
        "open": 9282.0,
        "high": 9379.0,
        "low": 9272.0,
        "close": 9355.0,
        "volume": 7,
        "hold": 495614
      },
      {
        "datetime": "2026-06-29 15:00:00",
        "open": 9355.0,
        "high": 9405.0,
        "low": 9336.0,
        "close": 9379.0,
        "volume": 233,
        "hold": 487520
      }
    ]
  }
}