{
  "updated_at_utc": "2026-07-17T06:08:18+00:00",
  "symbols": {
    "FCPO": {
      "name": "马来棕榈油",
      "price": 4554.46,
      "change": -19.54,
      "change_pct": "-0.43%",
      "source": "AKShare futures_foreign_commodity_realtime"
    },
    "SOYBEAN_OIL": {
      "name": "CBOT 豆油",
      "price": 71.049,
      "change": 0.479,
      "change_pct": "+0.68%",
      "source": "AKShare futures_foreign_commodity_realtime"
    },
    "BRENT": {
      "name": "布伦特原油",
      "price": 83.782,
      "change": -0.448,
      "change_pct": "-0.53%",
      "source": "AKShare futures_foreign_commodity_realtime"
    }
  }
}